sqpypitesting/__init__.py
sqpypitesting/__main__.py
sqpypitesting/resources/VERSION
sqpypitesting-0.0.3.dist-info/METADATA
sqpypitesting-0.0.3.dist-info/WHEEL
sqpypitesting-0.0.3.dist-info/licenses/LICENSE
sqpypitesting-0.0.3.dist-info/RECORD
