Metadata-Version: 2.3
Name: sqpypitesting
Version: 0.0.3
Summary: Testing package publication on pypi
Author-email: Sébastien Quistrebert <sebastien.quistrebert@ens-paris-saclay.fr>
License: The MIT License (MIT)
License-File: LICENSE
Requires-Python: >=3.7
